[
    {
        "key": "ctrl+e",
        "command": "workbench.action.quickOpenPreviousRecentlyUsedEditorInGroup"
    },
    {
        "key": "ctrl+shift+,",
        "command": "workbench.action.openRecent"
    },
    {
        "key": "ctrl+shift+j",
        "command": "editor.action.insertSnippet"
    },
    {
        "key": "ctrl+shift+g",
        "command": "editor.action.addSelectionToNextFindMatch"
    },
    {
        "key": "ctrl+alt+v",
        "command": "editor.action.insertSnippet",
        "args": {
            "name": "Extract As Variable"
        }
    },
    {
        "key": "ctrl+shift+/",
        "command": "editor.action.blockComment",
        "when": "editorTextFocus && !editorReadonly"
    },
    {
        "key": "ctrl+shift+k",
        "command": "git.pushTo"
    },
    {
        "key": "ctrl+q",
        "command": "-workbench.action.quit"
    },
    {
        "key": "ctrl+shift+=",
        "command": "-editor.unfoldAll",
        "when": "editorFocus"
    },
    {
        "key": "ctrl+-",
        "command": "-editor.fold",
        "when": "editorFocus"
    },
    {
        "key": "ctrl+0",
        "command": "-workbench.action.focusSideBar"
    },
    {
        "key": "ctrl+shift+=",
        "command": "-workbench.action.zoomIn"
    },
    {
        "key": "ctrl+numpad_add",
        "command": "-workbench.action.zoomIn"
    },
    {
        "key": "ctrl+=",
        "command": "-workbench.action.zoomIn"
    },
    {
        "key": "ctrl+-",
        "command": "-workbench.action.zoomOut"
    },
    {
        "key": "ctrl+numpad_subtract",
        "command": "-workbench.action.zoomOut"
    },
    {
        "key": "ctrl+numpad0",
        "command": "-workbench.action.zoomReset"
    },
    {
        "key": "ctrl+shift+=",
        "command": "editor.action.fontZoomIn"
    },
    {
        "key": "ctrl+-",
        "command": "editor.action.fontZoomOut"
    },
    {
        "key": "ctrl+0",
        "command": "editor.action.fontZoomReset"
    },
    {
        "key": "ctrl+shift+-",
        "command": "-editor.foldAll",
        "when": "editorFocus"
    },
    {
        "key": "shift+alt+down",
        "command": "-editor.action.moveLinesDownAction",
        "when": "editorTextFocus && !editorReadonly"
    },
    {
        "key": "shift+alt+up",
        "command": "-editor.action.moveLinesUpAction",
        "when": "editorTextFocus && !editorReadonly"
    },
    {
        "key": "ctrl+shift+tab",
        "command": "-workbench.action.quickOpenLeastRecentlyUsedEditorInGroup"
    },
    {
        "key": "ctrl+shift+tab",
        "command": "-workbench.action.quickOpenLeastRecentlyUsedEditorInGroup"
    },
    {
        "key": "ctrl+shift+backspace",
        "command": "-workbench.action.navigateToLastEditLocation"
    },
    {
        "key": "ctrl+shift+backspace",
        "command": "editor.action.deleteLines",
        "when": "editorTextFocus && !editorReadonly"
    },
]